{
  "version": "6.0",
  "nxVersion": "20.0.1",
  "pathMappings": {},
  "nxJsonPlugins": [],
  "pluginsConfig": {
    "@nx/js": {
      "analyzeSourceFiles": false
    }
  },
  "fileMap": {
    "nonProjectFiles": [
      {
        "file": ".eslintrc.js",
        "hash": "8600892946451210840"
      },
      {
        "file": ".gitignore",
        "hash": "12849909098603917362"
      },
      {
        "file": ".prettierrrc",
        "hash": "6462994994517180308"
      },
      {
        "file": ".vscode/extensions.json",
        "hash": "9966990234491576620"
      },
      {
        "file": ".vscode/settings.json",
        "hash": "13598060224294900289"
      },
      {
        "file": ".yarn/releases/yarn-4.5.0.cjs",
        "hash": "5212819997130390240"
      },
      {
        "file": ".yarn/sdks/eslint/bin/eslint.js",
        "hash": "14872269478262836979"
      },
      {
        "file": ".yarn/sdks/eslint/lib/api.js",
        "hash": "11935524110648288742"
      },
      {
        "file": ".yarn/sdks/eslint/lib/unsupported-api.js",
        "hash": "10989494384090494064"
      },
      {
        "file": ".yarn/sdks/eslint/package.json",
        "hash": "979153938861060082"
      },
      {
        "file": ".yarn/sdks/integrations.yml",
        "hash": "12213087882799053847"
      },
      {
        "file": ".yarn/sdks/prettier/bin/prettier.cjs",
        "hash": "1386140985451125376"
      },
      {
        "file": ".yarn/sdks/prettier/index.cjs",
        "hash": "3393616046143878484"
      },
      {
        "file": ".yarn/sdks/prettier/package.json",
        "hash": "15426012732732659717"
      },
      {
        "file": ".yarn/sdks/typescript/bin/tsc",
        "hash": "13885846455737793067"
      },
      {
        "file": ".yarn/sdks/typescript/bin/tsserver",
        "hash": "6819096246728401411"
      },
      {
        "file": ".yarn/sdks/typescript/lib/tsc.js",
        "hash": "2839614163630542371"
      },
      {
        "file": ".yarn/sdks/typescript/lib/tsserver.js",
        "hash": "1301760797202983736"
      },
      {
        "file": ".yarn/sdks/typescript/lib/tsserverlibrary.js",
        "hash": "1451277444867543573"
      },
      {
        "file": ".yarn/sdks/typescript/lib/typescript.js",
        "hash": "2824640601725886217"
      },
      {
        "file": ".yarn/sdks/typescript/package.json",
        "hash": "17138010724969792192"
      },
      {
        "file": ".yarnrc.yml",
        "hash": "891505033968280622"
      },
      {
        "file": "nx.json",
        "hash": "16737810001932659061"
      },
      {
        "file": "package.json",
        "hash": "3108555332675641170"
      },
      {
        "file": "tsconfig.base.json",
        "hash": "5239937699664684276"
      },
      {
        "file": "tsconfig.eslint.json",
        "hash": "14916243590591512667"
      },
      {
        "file": "yarn.lock",
        "hash": "17036440385163879119"
      }
    ],
    "projectFileMap": {
      "@designsystem/esbuild-config": [
        {
          "file": "packages/esbuild-config/README.md",
          "hash": "6886952344311067916"
        },
        {
          "file": "packages/esbuild-config/index.js",
          "hash": "8234093880769899929"
        },
        {
          "file": "packages/esbuild-config/package.json",
          "hash": "12789178505850411604",
          "deps": [
            "npm:esbuild@0.16.17"
          ]
        }
      ],
      "@designsystem/themes": [
        {
          "file": "packages/themes/build.js",
          "hash": "801618744610114148"
        },
        {
          "file": "packages/themes/package.json",
          "hash": "3982708235881043996",
          "deps": [
            "@designsystem/esbuild-config",
            "npm:typescript"
          ]
        },
        {
          "file": "packages/themes/scripts/build-css-module.js",
          "hash": "4007087392262096143"
        },
        {
          "file": "packages/themes/src/classes/index.ts",
          "hash": "16980293872951677454"
        },
        {
          "file": "packages/themes/src/classes/typography.ts",
          "hash": "1737226456848416719"
        },
        {
          "file": "packages/themes/src/index.ts",
          "hash": "12496849257317989786"
        },
        {
          "file": "packages/themes/src/variables/box.ts",
          "hash": "10900850870447942474"
        },
        {
          "file": "packages/themes/src/variables/colors/index.ts",
          "hash": "12796054265996578904"
        },
        {
          "file": "packages/themes/src/variables/colors/static/dark.ts",
          "hash": "11829123318318794238"
        },
        {
          "file": "packages/themes/src/variables/colors/static/index.ts",
          "hash": "6491624575104443728"
        },
        {
          "file": "packages/themes/src/variables/colors/static/light.ts",
          "hash": "8264435437772186195"
        },
        {
          "file": "packages/themes/src/variables/index.ts",
          "hash": "17309183189432464827"
        },
        {
          "file": "packages/themes/src/variables/typography.ts",
          "hash": "1888759767589057909"
        },
        {
          "file": "packages/themes/tsconfig.json",
          "hash": "9838581208239668351"
        }
      ]
    }
  }
}